stix_shifter_modules/tanium/__init__.py
stix_shifter_modules/tanium/entry_point.py
stix_shifter_modules/tanium/configuration/config.json
stix_shifter_modules/tanium/configuration/dialects.json
stix_shifter_modules/tanium/configuration/lang_en.json
stix_shifter_modules/tanium/stix_translation/__init__.py
stix_shifter_modules/tanium/stix_translation/json_to_stix_translator.py
stix_shifter_modules/tanium/stix_translation/query_constructor.py
stix_shifter_modules/tanium/stix_translation/query_translator.py
stix_shifter_modules/tanium/stix_translation/transformers.py
stix_shifter_modules/tanium/stix_translation/json/from_stix_map.json
stix_shifter_modules/tanium/stix_translation/json/operators.json
stix_shifter_modules/tanium/stix_translation/json/to_stix_map.json
stix_shifter_modules/tanium/stix_translation/json/stix_2_1/from_stix_map.json
stix_shifter_modules/tanium/stix_translation/json/stix_2_1/to_stix_map.json
stix_shifter_modules/tanium/stix_transmission/__init__.py
stix_shifter_modules/tanium/stix_transmission/connector.py
stix_shifter_modules/tanium/stix_transmission/error_mapper.py
stix_shifter_modules/tanium/stix_transmission/tanium_config.py
stix_shifter_modules/tanium/tests/__init__.py
stix_shifter_modules/tanium/tests/stix_translation/__init__.py
stix_shifter_modules/tanium/tests/stix_translation/test_from_json_to_stix.py
stix_shifter_modules/tanium/tests/stix_translation/test_from_stix_to_query.py
stix_shifter_modules/tanium/tests/stix_transmissions/__init__.py
stix_shifter_modules/tanium/tests/stix_transmissions/test_communicate_with_api.py
stix_shifter_modules_tanium-8.0.2.dist-info/licenses/AUTHORS.md
stix_shifter_modules_tanium-8.0.2.dist-info/licenses/LICENSE.md
stix_shifter_modules_tanium-8.0.2.dist-info/licenses/NOTICE
stix_shifter_modules_tanium-8.0.2.dist-info/METADATA
stix_shifter_modules_tanium-8.0.2.dist-info/WHEEL
stix_shifter_modules_tanium-8.0.2.dist-info/top_level.txt
stix_shifter_modules_tanium-8.0.2.dist-info/RECORD
